hazy-0.1.0.dist-info/METADATA
hazy-0.1.0.dist-info/WHEEL
hazy-0.1.0.dist-info/licenses/LICENSE
hazy/__init__.py
hazy/_compat.py
hazy/_hazy.cpython-312-darwin.so
hazy/_hazy.pyi
hazy/_helpers.py
hazy/_jupyter.py
hazy/py.typed
hazy/viz.py
hazy-0.1.0.dist-info/RECORD
