Metadata-Version: 2.4
Name: hazy
Version: 0.1.0
Classifier: Development Status :: 4 - Beta
Classifier: Intended Audience :: Developers
Classifier: Intended Audience :: Science/Research
Classifier: License :: OSI Approved :: MIT License
Classifier: Operating System :: OS Independent
Classifier: Programming Language :: Python :: 3
Classifier: Programming Language :: Python :: 3.9
Classifier: Programming Language :: Python :: 3.10
Classifier: Programming Language :: Python :: 3.11
Classifier: Programming Language :: Python :: 3.12
Classifier: Programming Language :: Python :: 3.13
Classifier: Programming Language :: Rust
Classifier: Topic :: Scientific/Engineering
Classifier: Topic :: Software Development :: Libraries :: Python Modules
Classifier: Typing :: Typed
Requires-Dist: numpy>=1.20 ; extra == 'numpy'
Requires-Dist: matplotlib>=3.5 ; extra == 'viz'
Requires-Dist: numpy>=1.20 ; extra == 'all'
Requires-Dist: matplotlib>=3.5 ; extra == 'all'
Requires-Dist: pytest>=7.0 ; extra == 'dev'
Requires-Dist: pytest-cov>=4.0 ; extra == 'dev'
Requires-Dist: hypothesis>=6.0 ; extra == 'dev'
Requires-Dist: numpy>=1.20 ; extra == 'dev'
Requires-Dist: matplotlib>=3.5 ; extra == 'dev'
Requires-Dist: maturin>=1.4 ; extra == 'dev'
Requires-Dist: ruff>=0.1.0 ; extra == 'dev'
Requires-Dist: mkdocs>=1.5 ; extra == 'docs'
Requires-Dist: mkdocs-material>=9.0 ; extra == 'docs'
Requires-Dist: mkdocstrings[python]>=0.24 ; extra == 'docs'
Provides-Extra: numpy
Provides-Extra: viz
Provides-Extra: all
Provides-Extra: dev
Provides-Extra: docs
License-File: LICENSE
Summary: A modern Python library for probabilistic data structures
Keywords: bloom-filter,hyperloglog,count-min-sketch,cuckoo-filter,probabilistic,data-structures,cardinality,streaming
Author: Caroline Haoud
License: MIT
Requires-Python: >=3.9
Project-URL: Homepage, https://github.com/carolinehaoud/hazy
Project-URL: Documentation, https://carolinehaoud.github.io/hazy
Project-URL: Repository, https://github.com/carolinehaoud/hazy
Project-URL: Issues, https://github.com/carolinehaoud/hazy/issues
